altiusone_ai/__init__.py
altiusone_ai/client.py
altiusone_ai/exceptions.py
altiusone_ai/schemas/__init__.py
altiusone_ai/schemas/contract.py
altiusone_ai/schemas/expense.py
altiusone_ai/schemas/identity.py
altiusone_ai/schemas/invoice.py
altiusone_ai/schemas/quote.py
altiusone_ai/schemas/resume.py
altiusone_ai-1.1.1.dist-info/METADATA
altiusone_ai-1.1.1.dist-info/WHEEL
altiusone_ai-1.1.1.dist-info/top_level.txt
altiusone_ai-1.1.1.dist-info/RECORD
