Metadata-Version: 2.4
Name: altiusone-ai
Version: 1.1.1
Summary: Python SDK for AltiusOne AI Service - OCR, Embeddings, Chat, and Extraction
Home-page: https://github.com/akouni/altiusoneai
Author: Altius Academy SNC
Author-email: Paul GUINDO <paulakounid@gmail.com>
Maintainer-email: Paul GUINDO <paulakounid@gmail.com>
License-Expression: LicenseRef-Proprietary
Project-URL: Homepage, https://altiusone.ch
Project-URL: Documentation, https://github.com/akouni/altiusoneai#readme
Project-URL: Repository, https://github.com/akouni/altiusoneai
Project-URL: API Documentation, https://ai.altiusone.ch/docs
Keywords: ai,embeddings,ocr,chat,nlp,machine-learning,altiusone
Classifier: Development Status :: 4 - Beta
Classifier: Intended Audience :: Developers
Classifier: Operating System :: OS Independent
Classifier: Programming Language :: Python :: 3
Classifier: Programming Language :: Python :: 3.9
Classifier: Programming Language :: Python :: 3.10
Classifier: Programming Language :: Python :: 3.11
Classifier: Programming Language :: Python :: 3.12
Classifier: Topic :: Scientific/Engineering :: Artificial Intelligence
Requires-Python: >=3.9
Requires-Dist: httpx>=0.28.0
Provides-Extra: dev
Requires-Dist: pytest>=8.0; extra == "dev"
Requires-Dist: pytest-asyncio>=0.24; extra == "dev"
Requires-Dist: black>=24.0; extra == "dev"
Requires-Dist: mypy>=1.13; extra == "dev"
Requires-Dist: ruff>=0.8.0; extra == "dev"
Dynamic: author
Dynamic: home-page
Dynamic: requires-python
